<?xml version="1.0" encoding="UTF-8"?>
<objects serializationModel="Studio.01.10.00">
    <object class="EncodingSetting" id="{9c437ffb-de2e-4b31-b4ae-8b1424fcc368}">
        <property name="encodingFormat">
            <value>3</value>
        </property>
        <property name="quality">
            <value>37</value>
        </property>
        <relationship name="platform">
            <destination>{80b2d681-80bd-408d-bbc7-c69a58987702}</destination>
        </relationship>
        <relationship name="encodable">
            <destination>{22bd9091-f0f9-4f5a-89a6-a298c5d130f3}</destination>
        </relationship>
    </object>
</objects>
